fedorainfra_ansible_messages/__init__.py
fedorainfra_ansible_messages/ansible_messages.py
fedorainfra_ansible_messages/distgit_messages.py
fedorainfra_ansible_messages/tests/__init__.py
fedorainfra_ansible_messages/tests/test_ansible_messages.py
fedorainfra_ansible_messages/tests/test_distgit_messages.py
fedorainfra_ansible_messages-0.0.2.dist-info/LICENSE
fedorainfra_ansible_messages-0.0.2.dist-info/METADATA
fedorainfra_ansible_messages-0.0.2.dist-info/WHEEL
fedorainfra_ansible_messages-0.0.2.dist-info/entry_points.txt
fedorainfra_ansible_messages-0.0.2.dist-info/top_level.txt
fedorainfra_ansible_messages-0.0.2.dist-info/RECORD
